[{"id":"'3'","description":"'В здоровом теле здоровый дух'","createdAt":"new Date('2018-02-14T18:20:00')","author":"'Kirill12'","photoLink":"'http://ont.by/webroot/delivery/files/news/2018/02/22/Dom.jpg'","hashtags":" ['sport', 'life']","likes":"['Ivan', 'Masha03']"},{"id":"'4'","description":"'Больше не могу придумывать подписи...'","createdAt":"new Date('2018-02-14T20:05:00')","author":"'Maxxxx'","photoLink":"'http://ont.by/webroot/delivery/files/news/2018/02/22/Dom.jpg'","hashtags":"['sport', 'life']","likes":"['Ivan', 'Masha03']"},{"id":"'5'","description":"'Классный кот.'","createdAt":"new Date('2018-02-14T21:20:00')","author":"'Violette'","photoLink":"'http://murkote.com/wp-content/uploads/2013/11/chem-kormit-siamskogo-kotenka.jpg'","hashtags":"['sport']","likes":"['289']"},{"id":"'6'","description":"'Very beautiful.'","createdAt":"new Date('2018-02-14T22:00:00')","author":"'Leo'","photoLink":"'https://likeni.info/wp-content/uploads/2017/01/1-33.jpg'","hashtags":"['sport', 'life']","likes":"['Ivan', 'Masha03']"},{"id":"'7'","description":"'Hello'","createdAt":"new Date('2018-02-14T23:00:00')","author":"'Olya'","photoLink":"'https://kulturologia.ru/files/u18476/adorable-dogs-9.jpg'","hashtags":"['sport', 'life']","likes":"['Ivan', 'Masha03']"},{"id":"'9'","description":"'Женская сборная Беларуси выиграла эстафету в рамках соревнований по биатлону на Олимпийских играх в Пхёнчхане!!!'","createdAt":"new Date('2018-02-15T07:40:00')","author":"'Kristina'","photoLink":"'http://ont.by/webroot/delivery/files/news/2018/02/22/Dom.jpg'","hashtags":" ['sport', 'life']","likes":"['Ivan', 'Masha03']"},{"id":"'10'","description":"'Женская сборная Беларуси выиграла эстафету в рамках соревнований по биатлону на Олимпийских играх в Пхёнчхане!!!'","createdAt":"new Date('2018-02-15T10:00:00')","author":"'Иванов23'","photoLink":"'http://ont.by/webroot/delivery/files/news/2018/02/22/Dom.jpg'","hashtags":"['sport', 'life']","likes":"['Ivan', 'Masha03']"}]